{
  "businessKey" : "object.rfParameterType.form.rfParameterTypeDefaultForm",
  "dataFormEventHandlers" : [ ],
  "dataObjectBusinessKey" : "object.rfParameterType",
  "defaultForm" : true,
  "description" : "Default form for RF Parameter Type",
  "enableSpellChecker" : true,
  "formControls" : [ {
    "businessKey" : "object.rfParameterType.form.rfParameterTypeDefaultForm.control.name",
    "dataElementBusinessKey" : "object.rfParameterType.element.name",
    "description" : "Name form control",
    "displayOrder" : 1,
    "formControlEventHandlers" : [ ],
    "formControlType" : "TEXT",
    "height" : 25,
    "label" : "Name",
    "labelControlBusinessKey" : null,
    "lookupBindingBusinessKey" : null,
    "mutableReadOnly" : false,
    "name" : "name",
    "readOnly" : false,
    "tooltipText" : null,
    "width" : 400,
    "x" : 0,
    "y" : 0
  }, {
    "businessKey" : "object.rfParameterType.form.rfParameterTypeDefaultForm.control.code",
    "dataElementBusinessKey" : "object.rfParameterType.element.code",
    "description" : "Code form control",
    "displayOrder" : 2,
    "formControlEventHandlers" : [ ],
    "formControlType" : "TEXT",
    "height" : 25,
    "label" : "Code",
    "labelControlBusinessKey" : null,
    "lookupBindingBusinessKey" : null,
    "mutableReadOnly" : false,
    "name" : "code",
    "readOnly" : false,
    "tooltipText" : null,
    "width" : 400,
    "x" : 0,
    "y" : 29
  }, {
    "businessKey" : "object.rfParameterType.form.rfParameterTypeDefaultForm.control.order",
    "dataElementBusinessKey" : "object.rfParameterType.element.order",
    "description" : "Order form control",
    "displayOrder" : 3,
    "formControlEventHandlers" : [ ],
    "formControlType" : "TEXT",
    "height" : 25,
    "label" : "Order",
    "labelControlBusinessKey" : null,
    "lookupBindingBusinessKey" : null,
    "mutableReadOnly" : false,
    "name" : "order",
    "readOnly" : false,
    "tooltipText" : null,
    "width" : 400,
    "x" : 0,
    "y" : 58
  } ],
  "instructions" : "<link type=\"text/css\" rel=\"stylesheet\" href=\"web-pub/aearchitecture/qtip/qtip.css\"/>\n<script type=\"text/javascript\" src=\"web-pub/aearchitecture/qtip/qtip.js\"></script>\n<script type=\"text/javascript\" src=\"page.request.do?page=tt.tooltip.utility\"></script>\n\n<script type=\"text/javascript\" src=\"page.request.do?page=aea.form.utilities.javascript\"></script>\n\n<script type=\"text/javascript\" src=\"page.request.do?page=rf.form.rfParameterType.javascript\"></script>",
  "layoutType" : "STACK",
  "name" : "RF Parameter Type Default Form",
  "offlineForm" : false,
  "scriptObjectBusinessKey" : null,
  "searchForm" : true,
  "title" : "RF Parameter Type"
}